autoopen/__init__.py
autoopen-0.1.0.dist-info/WHEEL
autoopen-0.1.0.dist-info/METADATA
autoopen-0.1.0.dist-info/RECORD
