Metadata-Version: 2.1
Name: autoopen
Version: 0.1.0
Summary: Automatically compress or decompress files on open by filename.
Home-page: https://github.com/thvitt/autoopen
License: MIT
Author: Thorsten Vitt
Author-email: tv@thorstenvitt.de
Requires-Python: >=3.9,<4.0
Classifier: License :: OSI Approved :: MIT License
Classifier: Programming Language :: Python :: 3
Classifier: Programming Language :: Python :: 3.10
Classifier: Programming Language :: Python :: 3.9
Provides-Extra: compressors
Requires-Dist: zstandard (>=0.17.0,<0.18.0); extra == "compressors"
Project-URL: Repository, https://github.com/thvitt/autoopen
